twingly_pyamqp/__init__.py
twingly_pyamqp/amqp_config.py
twingly_pyamqp/constants.py
twingly_pyamqp/publisher.py
twingly_pyamqp/subscription.py
twingly_pyamqp-0.2.3.dist-info/METADATA
twingly_pyamqp-0.2.3.dist-info/WHEEL
twingly_pyamqp-0.2.3.dist-info/RECORD
