Metadata-Version: 2.4
Name: twingly-pyamqp
Version: 0.2.3
Summary: A Python implementation for subscribing and publishing messages via RabbitMQ.
Author: Twingly AB
Requires-Python: >=3.11
Classifier: Programming Language :: Python :: 3
Classifier: Programming Language :: Python :: 3.11
Classifier: Programming Language :: Python :: 3.12
Classifier: Programming Language :: Python :: 3.13
Classifier: Programming Language :: Python :: 3.14
Requires-Dist: kombu (>=5.4.2,<6.0.0)
Requires-Dist: python-dotenv (>=1.0.1,<2.0.0)
